maahelper/__init__.py
maahelper/__main__.py
maahelper/cli_entry.py
maahelper/cli/__init__.py
maahelper/cli/modern_cli_selector.py
maahelper/cli/modern_enhanced_cli.py
maahelper/config/__init__.py
maahelper/config/config_manager.py
maahelper/core/__init__.py
maahelper/core/llm_client.py
maahelper/features/__init__.py
maahelper/features/git_integration.py
maahelper/features/model_discovery.py
maahelper/features/realtime_analysis.py
maahelper/ide/__init__.py
maahelper/ide/commands.py
maahelper/lsp/__init__.py
maahelper/lsp/handlers.py
maahelper/lsp/server.py
maahelper/managers/__init__.py
maahelper/managers/advanced_api_key_manager.py
maahelper/managers/streamlined_api_key_manager.py
maahelper/utils/__init__.py
maahelper/utils/input_validator.py
maahelper/utils/logging_system.py
maahelper/utils/memory_manager.py
maahelper/utils/rate_limiter.py
maahelper/utils/streaming.py
maahelper/utils/streamlined_file_handler.py
maahelper/vibecoding/__init__.py
maahelper/vibecoding/commands.py
maahelper/vibecoding/prompts.py
maahelper/vibecoding/workflow.py
maahelper/workflows/__init__.py
maahelper/workflows/commands.py
maahelper/workflows/engine.py
maahelper/workflows/nodes.py
maahelper/workflows/state.py
maahelper/workflows/templates.py
maahelper-0.0.5.dist-info/licenses/LICENSE
maahelper-0.0.5.dist-info/METADATA
maahelper-0.0.5.dist-info/WHEEL
maahelper-0.0.5.dist-info/entry_points.txt
maahelper-0.0.5.dist-info/top_level.txt
maahelper-0.0.5.dist-info/RECORD
