Metadata-Version: 2.4
Name: maahelper
Version: 0.0.5
Summary: MaaHelper - Advanced AI-powered coding assistant with real-time analysis and Git integration
Home-page: https://github.com/AIMLDev726/maahelper
Author: AIStudent
Author-email: AIStudent <aistudentlearn4@gmail.com>
Maintainer: AIMLDev726
Maintainer-email: AIMLDev726 <aistudentlearn4@gmail.com>
License-Expression: MIT
Project-URL: Homepage, https://github.com/AIMLDev726/maahelper
Project-URL: Documentation, https://github.com/AIMLDev726/maahelper#readme
Project-URL: Repository, https://github.com/AIMLDev726/maahelper
Project-URL: Bug Tracker, https://github.com/AIMLDev726/maahelper/issues
Project-URL: Changelog, https://github.com/AIMLDev726/maahelper/blob/main/CHANGELOG.md
Keywords: ai,assistant,code-analysis,bug-fixing,automation
Classifier: Development Status :: 4 - Beta
Classifier: Intended Audience :: Developers
Classifier: Topic :: Software Development :: Libraries :: Python Modules
Classifier: Topic :: Software Development :: Quality Assurance
Classifier: Topic :: Software Development :: Code Generators
Classifier: Topic :: Scientific/Engineering :: Artificial Intelligence
Classifier: Programming Language :: Python :: 3
Classifier: Programming Language :: Python :: 3.8
Classifier: Programming Language :: Python :: 3.9
Classifier: Programming Language :: Python :: 3.10
Classifier: Programming Language :: Python :: 3.11
Classifier: Programming Language :: Python :: 3.12
Classifier: Operating System :: OS Independent
Classifier: Environment :: Console
Requires-Python: >=3.8
License-File: LICENSE
Requires-Dist: openai>=1.0.0
Requires-Dist: rich>=13.0.0
Requires-Dist: structlog>=23.0.0
Requires-Dist: cryptography>=3.4.0
Requires-Dist: aiohttp>=3.8.0
Requires-Dist: watchdog>=3.0.0
Requires-Dist: gitpython>=3.1.0
Requires-Dist: pathlib2; python_version < "3.4"
Requires-Dist: googlesearch-python>=1.2.0
Requires-Dist: typing-extensions>=4.0.0; python_version < "3.10"
Requires-Dist: aiofiles>=23.0.0
Requires-Dist: pygls>=1.0.0; extra == "lsp"
Provides-Extra: dev
Requires-Dist: pytest>=6.0; extra == "dev"
Requires-Dist: pytest-cov; extra == "dev"
Requires-Dist: black; extra == "dev"
Requires-Dist: flake8; extra == "dev"
Requires-Dist: mypy; extra == "dev"
Requires-Dist: pre-commit; extra == "dev"
Provides-Extra: test
Requires-Dist: pytest>=6.0; extra == "test"
Requires-Dist: pytest-cov; extra == "test"
Provides-Extra: lsp
Requires-Dist: pygls>=1.0.0; extra == "lsp"
Provides-Extra: ide
Requires-Dist: pygls>=1.0.0; extra == "ide"
Requires-Dist: aiofiles>=23.0.0; extra == "ide"
Provides-Extra: workflows
Requires-Dist: aiofiles>=23.0.0; extra == "workflows"
Dynamic: author
Dynamic: home-page
Dynamic: license-file
Dynamic: maintainer
Dynamic: requires-python
